targetDB/__init__.py
targetDB/cns_mpo.py
targetDB/drugg_errors.py
targetDB/druggability_DB.py
targetDB/druggability_report.py
targetDB/target_descriptors.py
targetDB/target_features.py
targetDB/data/BindingDB_12_12_19.zip
targetDB/data/drugEbility_domains_01_08_18.zip
targetDB/data/drugEbility_sites_01_08_18.zip
targetDB/data/hgnc_12_12_19.zip
targetDB/data/pdb_bind_21_01_2020.zip
targetDB/data/purchasable_compounds_12_12_19.zip
targetDB/data/tcrd_disease_19_02_19.zip
targetDB/data/tcrd_id_12_12_19.zip
targetDB/data/tcrd_info_12_12_19.zip
targetDB/data/tcrd_novelty_12_12_19.zip
targetDB/data/tcrd_patent_12_12_19.zip
targetDB/data/tcrd_target_12_12_19.zip
targetDB/ml_data/ml_training_data_13_01_2020.zip
targetDB/protein_atlas_api/__init__.py
targetDB/protein_atlas_api/proteinatlas.py
targetDB/resources/APOE_Spider.png
targetDB/resources/Figure_spider_plot_legend.png
targetDB/resources/TargetDB_list_output_columns_definition.xlsx
targetDB/resources/TargetDB_tutorial.pdf
targetDB/resources/configuration.png
targetDB/resources/target_DB_command.png
targetDB/resources/targetdb_gui.png
targetDB/utils/__init__.py
targetDB/utils/config.py
targetDB/utils/db_connection.py
targetDB/utils/druggability_ml.py
targetDB/utils/gene2id.py
targetDB/utils/pdb_parser.py
targetDB/utils/pocket_finder.py
targetDB/utils/retryers.py
targetDB/utils/tabcompleter.py
targetDB/utils/targetDB_gui.py
targetDB/utils/targetDB_init.py
targetDB/utils/uniprot_parse.py
targetDB-1.3.3.dist-info/LICENSE
targetDB-1.3.3.dist-info/METADATA
targetDB-1.3.3.dist-info/WHEEL
targetDB-1.3.3.dist-info/entry_points.txt
targetDB-1.3.3.dist-info/top_level.txt
targetDB-1.3.3.dist-info/RECORD
