Metadata-Version: 2.1
Name: targetDB
Version: 1.3.3
Summary: Package with an application to generate report on potential drug targets
Home-page: https://github.com/sdecesco/targetDB
Author: Stephane De Cesco
Author-email: sdecesco@gmail.com
License: UNKNOWN
Platform: UNKNOWN
Classifier: Programming Language :: Python :: 3
Classifier: Development Status :: 4 - Beta
Classifier: Intended Audience :: Science/Research
Classifier: License :: OSI Approved :: GNU General Public License v3 or later (GPLv3+)
Classifier: Operating System :: OS Independent
Classifier: Programming Language :: Python :: 3 :: Only
License-File: LICENSE
Requires-Dist: biopython
Requires-Dist: scipy
Requires-Dist: matplotlib
Requires-Dist: pandas (>=0.21.0)
Requires-Dist: intermine
Requires-Dist: xmltodict
Requires-Dist: xlsxwriter
